{
  "id": "e00b41dc-44a2-40c6-b188-fecbb513eca1",
  "prevId": "47a60bbf-37da-47c1-baac-1caf103a8ba1",
  "version": "7",
  "dialect": "postgresql",
  "tables": {
    "public.native_login_otc": {
      "name": "native_login_otc",
      "schema": "",
      "columns": {
        "code": {
          "name": "code",
          "type": "text",
          "primaryKey": true,
          "notNull": true
        },
        "payload": {
          "name": "payload",
          "type": "jsonb",
          "primaryKey": false,
          "notNull": true
        },
        "expires_at": {
          "name": "expires_at",
          "type": "timestamp with time zone",
          "primaryKey": false,
          "notNull": true
        }
      },
      "indexes": {},
      "foreignKeys": {},
      "compositePrimaryKeys": {},
      "uniqueConstraints": {},
      "policies": {},
      "checkConstraints": {},
      "isRLSEnabled": false
    },
    "public.organizations": {
      "name": "organizations",
      "schema": "",
      "columns": {
        "id": {
          "name": "id",
          "type": "uuid",
          "primaryKey": true,
          "notNull": true,
          "default": "gen_random_uuid()"
        },
        "tenant_id": {
          "name": "tenant_id",
          "type": "text",
          "primaryKey": false,
          "notNull": true
        },
        "name": {
          "name": "name",
          "type": "text",
          "primaryKey": false,
          "notNull": true
        },
        "trade_slug": {
          "name": "trade_slug",
          "type": "text",
          "primaryKey": false,
          "notNull": true
        },
        "created_at": {
          "name": "created_at",
          "type": "timestamp with time zone",
          "primaryKey": false,
          "notNull": true,
          "default": "now()"
        }
      },
      "indexes": {},
      "foreignKeys": {},
      "compositePrimaryKeys": {},
      "uniqueConstraints": {
        "organizations_tenant_id_unique": {
          "name": "organizations_tenant_id_unique",
          "nullsNotDistinct": false,
          "columns": [
            "tenant_id"
          ]
        }
      },
      "policies": {},
      "checkConstraints": {},
      "isRLSEnabled": false
    },
    "public.projects": {
      "name": "projects",
      "schema": "",
      "columns": {
        "id": {
          "name": "id",
          "type": "uuid",
          "primaryKey": true,
          "notNull": true,
          "default": "gen_random_uuid()"
        },
        "tenant_id": {
          "name": "tenant_id",
          "type": "text",
          "primaryKey": false,
          "notNull": true
        },
        "title": {
          "name": "title",
          "type": "text",
          "primaryKey": false,
          "notNull": true
        },
        "created_at": {
          "name": "created_at",
          "type": "timestamp with time zone",
          "primaryKey": false,
          "notNull": true,
          "default": "now()"
        },
        "updated_at": {
          "name": "updated_at",
          "type": "timestamp with time zone",
          "primaryKey": false,
          "notNull": true,
          "default": "now()"
        }
      },
      "indexes": {},
      "foreignKeys": {
        "projects_tenant_id_organizations_tenant_id_fk": {
          "name": "projects_tenant_id_organizations_tenant_id_fk",
          "tableFrom": "projects",
          "tableTo": "organizations",
          "columnsFrom": [
            "tenant_id"
          ],
          "columnsTo": [
            "tenant_id"
          ],
          "onDelete": "cascade",
          "onUpdate": "no action"
        }
      },
      "compositePrimaryKeys": {},
      "uniqueConstraints": {},
      "policies": {},
      "checkConstraints": {},
      "isRLSEnabled": false
    },
    "public.sync_mutation_receipts": {
      "name": "sync_mutation_receipts",
      "schema": "",
      "columns": {
        "id": {
          "name": "id",
          "type": "uuid",
          "primaryKey": true,
          "notNull": true,
          "default": "gen_random_uuid()"
        },
        "tenant_id": {
          "name": "tenant_id",
          "type": "text",
          "primaryKey": false,
          "notNull": true
        },
        "idempotency_key": {
          "name": "idempotency_key",
          "type": "uuid",
          "primaryKey": false,
          "notNull": true
        },
        "device_id": {
          "name": "device_id",
          "type": "uuid",
          "primaryKey": false,
          "notNull": true
        },
        "entity_type": {
          "name": "entity_type",
          "type": "text",
          "primaryKey": false,
          "notNull": true
        },
        "operation": {
          "name": "operation",
          "type": "text",
          "primaryKey": false,
          "notNull": true
        },
        "payload": {
          "name": "payload",
          "type": "jsonb",
          "primaryKey": false,
          "notNull": true
        },
        "result_entity_id": {
          "name": "result_entity_id",
          "type": "uuid",
          "primaryKey": false,
          "notNull": false
        },
        "created_at": {
          "name": "created_at",
          "type": "timestamp with time zone",
          "primaryKey": false,
          "notNull": true,
          "default": "now()"
        }
      },
      "indexes": {},
      "foreignKeys": {
        "sync_mutation_receipts_tenant_id_organizations_tenant_id_fk": {
          "name": "sync_mutation_receipts_tenant_id_organizations_tenant_id_fk",
          "tableFrom": "sync_mutation_receipts",
          "tableTo": "organizations",
          "columnsFrom": [
            "tenant_id"
          ],
          "columnsTo": [
            "tenant_id"
          ],
          "onDelete": "cascade",
          "onUpdate": "no action"
        }
      },
      "compositePrimaryKeys": {},
      "uniqueConstraints": {
        "sync_mutation_receipts_tenant_idempotency": {
          "name": "sync_mutation_receipts_tenant_idempotency",
          "nullsNotDistinct": false,
          "columns": [
            "tenant_id",
            "idempotency_key"
          ]
        }
      },
      "policies": {},
      "checkConstraints": {},
      "isRLSEnabled": false
    }
  },
  "enums": {},
  "schemas": {},
  "sequences": {},
  "roles": {},
  "policies": {},
  "views": {},
  "_meta": {
    "columns": {},
    "schemas": {},
    "tables": {}
  }
}